README.md
setup.cfg
setup.py
distributions/Binomialdistribution.py
distributions/Gaussiandistribution.py
distributions/Generaldistribution.py
distributions/__init__.py
vu13_distributions.egg-info/PKG-INFO
vu13_distributions.egg-info/SOURCES.txt
vu13_distributions.egg-info/dependency_links.txt
vu13_distributions.egg-info/not-zip-safe
vu13_distributions.egg-info/top_level.txt